pyselect.py
pyselect/__init__.py
pyselect/pyselect.py
pyselect-0.2.0.dist-info/DESCRIPTION.rst
pyselect-0.2.0.dist-info/METADATA
pyselect-0.2.0.dist-info/pydist.json
pyselect-0.2.0.dist-info/RECORD
pyselect-0.2.0.dist-info/top_level.txt
pyselect-0.2.0.dist-info/WHEEL
