Metadata-Version: 2.0
Name: pyselect
Version: 0.2.0
Summary: A Python library for easily getting user input form multiple items in a list, emulating the Bash(1) builtin select.
Home-page: https://github.com/askedrelic/pyselect
Author: Matthew Behrens
Author-email: askedrelic@gmail.com
License: The MIT License (MIT)
